{
  "schema_version": 1,
  "namespace": "myst/accounts",
  "record_id": "slmkhanahmed",
  "revision": 151,
  "status": "saturated",
  "payload": {
    "account_id": "slmkhanahmed",
    "wallet_index": 0,
    "wallet_address": "0xfa5Ed99C47a2Afc4b5340f565e8f9c019aF788fc",
    "persistent_profile_dir": "",
    "wallet_onboarding_status": "ready",
    "generation": 0,
    "status": "saturated",
    "source": "bootstrap",
    "created_by": "myst-node-v2-01",
    "saturated_reason": "The page states the mystnodes account has reached the free-node registration limit and requires the standard onboarding process, blocking automated completion.",
    "failure_reason": "",
    "created_at": "2026-03-30T06:21:53.344162+00:00",
    "updated_at": "2026-04-04T02:23:44.436102+00:00"
  },
  "secrets_encrypted": "5g7yDejFzS1Edvffd+ecog8UKNrCG3jHC4yHzRTGYUkqx3/UFh9Ts844rqV2GDEXA9qa4NcQNOWwZPQEw9bFgZzyc7Ur9lDHsXr4vn01nZu1pK3YAXmJ7epu3xfKePod",
  "owner": "d17e85f64c0e",
  "created_at": "2026-03-30T06:21:54.780456Z",
  "updated_at": "2026-04-04T02:23:44.436326Z",
  "lease": null,
  "tags": [
    "myst",
    "account_pool"
  ],
  "metadata": {
    "wallet_index": 0,
    "wallet_address": "0xfa5Ed99C47a2Afc4b5340f565e8f9c019aF788fc",
    "persistent_profile_dir": "",
    "wallet_onboarding_status": "ready",
    "generation": 0,
    "source": "bootstrap"
  }
}